gdelttools/__init__.py
gdelttools/_version.py
gdelttools/gdeltexample.py
gdelttools/gdeltfile.py
gdelttools/gdeltloader.py
gdelttools/gdeltwebdata.py
gdelttools/mapgeolocation.py
gdelttools/mongoimport.py
gdelttools/validator.py
gdelttools/web.py
gdelttools-0.7b2.dist-info/LICENSE
gdelttools-0.7b2.dist-info/METADATA
gdelttools-0.7b2.dist-info/WHEEL
gdelttools-0.7b2.dist-info/entry_points.txt
gdelttools-0.7b2.dist-info/top_level.txt
gdelttools-0.7b2.dist-info/RECORD
