Metadata-Version: 2.1
Name: gdelttools
Version: 0.7b2
Summary: A set of tools to support downloading GDELT data
Home-page: https://github.com/jdrumgoole/gdelttools
Author: Joe Drumgoole
Author-email: joe@joedrumgoole.com
License: Apache 2.0
Keywords: MongoDB GDELT dataset
Platform: UNKNOWN
Classifier: Development Status :: 3 - Alpha
Classifier: Intended Audience :: Developers
Classifier: License :: OSI Approved :: Apache Software License
Classifier: Operating System :: OS Independent
Classifier: Programming Language :: Python
Classifier: Programming Language :: Python :: 3.7
Classifier: Programming Language :: Python :: 3.8
Requires-Python: >3.7
License-File: LICENSE
Requires-Dist: pymongo
Requires-Dist: requests
